{
  "n_races": 25,
  "lanes": {
    "1": {
      "effect": 3.7482,
      "se": 4.6753,
      "n": 7,
      "p": 0.5408,
      "sig": ""
    },
    "2": {
      "effect": 0.8479,
      "se": 2.7409,
      "n": 23,
      "p": 0.8292,
      "sig": ""
    },
    "3": {
      "effect": 5.2707,
      "se": 2.7935,
      "n": 23,
      "p": 0.179,
      "sig": ""
    },
    "4": {
      "effect": 4.2376,
      "se": 2.6642,
      "n": 25,
      "p": 0.2677,
      "sig": ""
    },
    "5": {
      "effect": 0.0,
      "se": 2.6642,
      "n": 25,
      "p": 1.0,
      "sig": ""
    },
    "6": {
      "effect": 4.3801,
      "se": 3.4848,
      "n": 13,
      "p": 0.3621,
      "sig": ""
    }
  },
  "p_overall": 0.715,
  "sig_overall": false,
  "reference_lane": 5,
  "model": "lmm_sum_coding"
}