{
  "n_races": 31,
  "lanes": {
    "1": {
      "effect": 0.0,
      "se": 2.5986,
      "n": 11,
      "p": 1.0,
      "sig": ""
    },
    "2": {
      "effect": 5.4951,
      "se": 1.728,
      "n": 31,
      "p": 0.1453,
      "sig": ""
    },
    "3": {
      "effect": 7.3364,
      "se": 1.728,
      "n": 31,
      "p": 0.0519,
      "sig": "\u2020"
    },
    "4": {
      "effect": 7.7351,
      "se": 1.8146,
      "n": 26,
      "p": 0.0426,
      "sig": "*"
    }
  },
  "p_overall": 0.1859,
  "sig_overall": false,
  "reference_lane": 1,
  "model": "lmm_sum_coding"
}