{
  "n_races": 68,
  "lanes": {
    "1": {
      "effect": 0.0,
      "se": 2.6278,
      "n": 25,
      "p": 1.0,
      "sig": ""
    },
    "2": {
      "effect": 4.1784,
      "se": 1.6913,
      "n": 65,
      "p": 0.2378,
      "sig": ""
    },
    "3": {
      "effect": 8.5784,
      "se": 1.6618,
      "n": 68,
      "p": 0.015,
      "sig": "*"
    },
    "4": {
      "effect": 3.679,
      "se": 1.6618,
      "n": 68,
      "p": 0.2967,
      "sig": ""
    },
    "5": {
      "effect": 4.4867,
      "se": 1.6618,
      "n": 68,
      "p": 0.2031,
      "sig": ""
    },
    "6": {
      "effect": 8.3599,
      "se": 1.8013,
      "n": 56,
      "p": 0.02,
      "sig": "*"
    }
  },
  "p_overall": 0.0616,
  "sig_overall": false,
  "reference_lane": 1,
  "model": "lmm_sum_coding"
}