{
  "n_races": 55,
  "lanes": {
    "1": {
      "effect": 11.9724,
      "se": 1.9961,
      "n": 47,
      "p": 0.0126,
      "sig": "*"
    },
    "2": {
      "effect": 11.6153,
      "se": 1.8802,
      "n": 55,
      "p": 0.0145,
      "sig": "*"
    },
    "3": {
      "effect": 15.7911,
      "se": 1.8802,
      "n": 55,
      "p": 0.0009,
      "sig": "***"
    },
    "4": {
      "effect": 14.5336,
      "se": 1.8802,
      "n": 55,
      "p": 0.0022,
      "sig": "**"
    },
    "5": {
      "effect": 8.3699,
      "se": 2.249,
      "n": 35,
      "p": 0.0882,
      "sig": "\u2020"
    },
    "6": {
      "effect": 0.0,
      "se": 3.688,
      "n": 12,
      "p": 1.0,
      "sig": ""
    }
  },
  "p_overall": 0.0114,
  "sig_overall": true,
  "reference_lane": 6,
  "model": "lmm_sum_coding"
}