{
  "n_races": 28,
  "lanes": {
    "3": {
      "effect": 4.7328,
      "se": 3.5562,
      "n": 11,
      "p": 0.3239,
      "sig": ""
    },
    "4": {
      "effect": 6.275,
      "se": 2.3061,
      "n": 28,
      "p": 0.0694,
      "sig": "\u2020"
    },
    "5": {
      "effect": 2.6604,
      "se": 2.3061,
      "n": 28,
      "p": 0.4414,
      "sig": ""
    },
    "6": {
      "effect": 0.0,
      "se": 2.3061,
      "n": 28,
      "p": 1.0,
      "sig": ""
    },
    "7": {
      "effect": 5.565,
      "se": 2.3061,
      "n": 28,
      "p": 0.1073,
      "sig": ""
    },
    "8": {
      "effect": 1.736,
      "se": 2.4194,
      "n": 25,
      "p": 0.6279,
      "sig": ""
    }
  },
  "p_overall": 0.438,
  "sig_overall": false,
  "reference_lane": 6,
  "model": "lmm_sum_coding"
}